gpapi/__init__.py
gpapi/config.py
gpapi/device.properties
gpapi/googleplay.py
gpapi/googleplay_pb2.py
gpapi/utils.py
test_google_play_api-1.0.14.dist-info/LICENSE.md
test_google_play_api-1.0.14.dist-info/METADATA
test_google_play_api-1.0.14.dist-info/WHEEL
test_google_play_api-1.0.14.dist-info/top_level.txt
test_google_play_api-1.0.14.dist-info/RECORD
